setup.py
aarrr/__init__.py
aarrr/__main__.py
aarrr/command_line.py
aarrr.egg-info/PKG-INFO
aarrr.egg-info/SOURCES.txt
aarrr.egg-info/dependency_links.txt
aarrr.egg-info/entry_points.txt
aarrr.egg-info/not-zip-safe
aarrr.egg-info/top_level.txt
bin/aarrr