Metadata-Version: 1.0
Name: aarrr
Version: 0.1
Summary: aarrr
Home-page: http://github.com/AARRR/aarrr.py
Author: Inndy
Author-email: inndy.tw@gmail.com
License: MIT
Keywords: aarrr
Platform: UNKNOWN
